[
    {
        "id": 1,
        "imagen": "https://i.ibb.co/hdyFWCV/ppt1.jpg"
    },

  {
        "id": 2,
        "imagen": "https://i.ibb.co/yNZtBW7/ppt2.jpg"
    },
  {
        "id": 3,
        "imagen": "https://i.ibb.co/N36QnQR/ppt3.jpg"
    },
  {
        "id": 4,
        "imagen": "https://i.ibb.co/TTfXJGG/ppt4.jpg"
    },
  {
        "id": 5,
        "imagen": "https://i.ibb.co/Wpb8qpK/ppt5.jpg"
    },
  {
        "id": 6,
        "imagen": "https://i.ibb.co/6FKTRFg/ppt6.jpg"
    },
  {
        "id": 7,
        "imagen": "https://i.ibb.co/Gsz7fdM/ppt7.jpg"
    },
  {
        "id": 8,
        "imagen": "https://i.ibb.co/DM9NJf7/ppt8.jpg"
    },
  {
        "id": 9,
        "imagen": "https://i.ibb.co/Sx7NPBn/ppt9.jpg"
    },
  {
        "id": 10,
        "imagen": "https://i.ibb.co/FDK49CC/ppt10.jpg"
    },
    {
        "id": 11,
        "imagen": "https://i.ibb.co/1zVvR0p/ppt11.jpg"
    },
    {
        "id": 12,
        "imagen": "https://i.ibb.co/rxFRHKj/ppt12.jpg"
    },
    {
        "id": 13,
        "imagen": "https://i.ibb.co/vVJrbjB/ppt13.jpg"
    }
]